geodude/__init__.py
geodude/cluster_functions.py
geodude-0.0.1.dist-info/LICENSE
geodude-0.0.1.dist-info/METADATA
geodude-0.0.1.dist-info/WHEEL
geodude-0.0.1.dist-info/top_level.txt
geodude-0.0.1.dist-info/RECORD
